dubhubinstrument/__init__.py
opentelemetry/instrumentation/psycopg2/__init__.py
opentelemetry/instrumentation/psycopg2/package.py
opentelemetry/instrumentation/psycopg2/version.py
dubhub_instrument_psycopg2-0.34b2.dist-info/METADATA
dubhub_instrument_psycopg2-0.34b2.dist-info/WHEEL
dubhub_instrument_psycopg2-0.34b2.dist-info/entry_points.txt
dubhub_instrument_psycopg2-0.34b2.dist-info/licenses/LICENSE
dubhub_instrument_psycopg2-0.34b2.dist-info/RECORD
