Metadata-Version: 2.1
Name: dubhub-instrument-psycopg2
Version: 0.34b2
Summary: DubHub fork of OpenTelemetry psycopg2 instrumentation
Project-URL: Homepage, https://github.com/open-telemetry/opentelemetry-python-contrib/tree/main/instrumentation/opentelemetry-instrumentation-psycopg2
Author-email: OpenTelemetry Authors <cncf-opentelemetry-contributors@lists.cncf.io>
License-File: LICENSE
Classifier: Development Status :: 4 - Beta
Classifier: Intended Audience :: Developers
Classifier: License :: OSI Approved :: Apache Software License
Classifier: Programming Language :: Python
Classifier: Programming Language :: Python :: 3
Classifier: Programming Language :: Python :: 3.7
Classifier: Programming Language :: Python :: 3.8
Classifier: Programming Language :: Python :: 3.9
Classifier: Programming Language :: Python :: 3.10
Requires-Python: >=3.7
Requires-Dist: opentelemetry-api~=1.12
Requires-Dist: opentelemetry-exporter-otlp==1.13.0
Requires-Dist: opentelemetry-instrumentation-dbapi==0.34b0
Requires-Dist: opentelemetry-instrumentation-django==0.34b0
Requires-Dist: opentelemetry-instrumentation==0.34b0
Provides-Extra: instruments
Requires-Dist: psycopg2>=2.7.3.1; extra == 'instruments'
Provides-Extra: test
Requires-Dist: opentelemetry-instrumentation-psycopg2[instruments]; extra == 'test'
Requires-Dist: opentelemetry-test-utils==0.34b0; extra == 'test'
